simplyprint_ws_client/__init__.py
simplyprint_ws_client/__main__.py
simplyprint_ws_client/ambient.py
simplyprint_ws_client/async_loop.py
simplyprint_ws_client/client.py
simplyprint_ws_client/config.py
simplyprint_ws_client/connection.py
simplyprint_ws_client/const.py
simplyprint_ws_client/event.py
simplyprint_ws_client/file.py
simplyprint_ws_client/printer_state.py
simplyprint_ws_client/timer.py
simplyprint_ws_client-0.0.6.dist-info/LICENSE
simplyprint_ws_client-0.0.6.dist-info/METADATA
simplyprint_ws_client-0.0.6.dist-info/WHEEL
simplyprint_ws_client-0.0.6.dist-info/RECORD
