Metadata-Version: 2.1
Name: simplyprint-ws-client
Version: 0.0.6
Summary: SimplyPrint Websocket Client
Home-page: https://simplyprint.io
License: AGPL-3.0-or-later
Keywords: simplyprint,websocket,client
Author: SimplyPrint
Author-email: contact@simplyprint.io
Requires-Python: >=3.10,<4.0
Classifier: License :: OSI Approved :: GNU Affero General Public License v3 or later (AGPLv3+)
Classifier: Programming Language :: Python :: 3
Classifier: Programming Language :: Python :: 3.10
Classifier: Programming Language :: Python :: 3.11
Requires-Dist: netifaces (>=0.11.0,<0.12.0)
Requires-Dist: opencv-python (>=4.7.0.72,<5.0.0.0)
Requires-Dist: psutil (>=5.9.4,<6.0.0)
Requires-Dist: requests (>=2.28.2,<3.0.0)
Requires-Dist: sentry-sdk (>=1.18.0,<2.0.0)
Requires-Dist: tornado (>=6.2,<7.0)
Project-URL: Bug Tracker, https://github.com/SimplyPrint/printer-ws-client/issues
Project-URL: Repository, https://github.com/SimplyPrint/printer-ws-client
